setup.cfg
setup.py
bin/tracknodes
lib/tracknodes/__init__.py
lib/tracknodes/cli.py
lib/tracknodes/tracknodes.py
lib/tracknodes.egg-info/PKG-INFO
lib/tracknodes.egg-info/SOURCES.txt
lib/tracknodes.egg-info/dependency_links.txt
lib/tracknodes.egg-info/requires.txt
lib/tracknodes.egg-info/top_level.txt