Metadata-Version: 1.1
Name: tracknodes
Version: 1.0.1
Summary: Tracknodes keeps a history of node state and comment changes. It allows system administrators of HPC systems to determine when nodes were down and discover trends such as recurring issues. Supports Torque and PBSpro and has limited support for SLURM.
Home-page: https://github.com/NREL/tracknodes
Author: David Whiteside
Author-email: david.whiteside@nrel.gov
License: GPL
Platform: UNKNOWN
Classifier: Environment :: Console
Classifier: Intended Audience :: Information Technology
Classifier: Intended Audience :: System Administrators
Classifier: Natural Language :: English
Classifier: Operating System :: POSIX
Classifier: Programming Language :: Python :: 2.6
Classifier: Programming Language :: Python :: 2.7
Classifier: Topic :: System :: Installation/Setup
Classifier: Topic :: System :: Systems Administration
Classifier: Topic :: Utilities
